scss_compile/__init__.py
scss_compile-0.1.3.dist-info/LICENSE
scss_compile-0.1.3.dist-info/METADATA
scss_compile-0.1.3.dist-info/WHEEL
scss_compile-0.1.3.dist-info/entry_points.txt
scss_compile-0.1.3.dist-info/top_level.txt
scss_compile-0.1.3.dist-info/RECORD
