Metadata-Version: 2.1
Name: scss-compile
Version: 0.1.3
Summary: A CLI for compiling SCSS files to CSS, and associated pre-commit hook.
Home-page: https://github.com/executablebooks/scss-compile
Author: Chris Sewell
Author-email: chrisj_sewell@hotmail.com
License: MIT
Keywords: sass scss compile pre-commit
Platform: UNKNOWN
Classifier: License :: OSI Approved :: MIT License
Classifier: Programming Language :: Python :: 3
Requires-Python: >=3.6
Requires-Dist: click (~=7.1.2)
Requires-Dist: click-config-file (~=0.6.0)
Requires-Dist: libsass (~=0.20.1)
Requires-Dist: gitpython (~=3.1.8)
Requires-Dist: pyyaml
Requires-Dist: toml
Provides-Extra: testing
Requires-Dist: pytest (~=6.0.1) ; extra == 'testing'
